README.rst
setup.py
inr_to_words/__init__.py
inr_to_words/amount_to_text.py
inr_to_words.egg-info/PKG-INFO
inr_to_words.egg-info/SOURCES.txt
inr_to_words.egg-info/dependency_links.txt
inr_to_words.egg-info/not-zip-safe
inr_to_words.egg-info/top_level.txt