Metadata-Version: 1.1
Name: inr-to-words
Version: 1.1.1
Summary: Convert Amount in INR to words in Indian Numbering System
Home-page: https://gitlab.com/albin_john/inr_to_words
Author: Albin John
Author-email: albinjohn54@gmail.com
License: MIT
Keywords: convert money words indian development
Platform: UNKNOWN
Classifier: Development Status :: 3 - Alpha
Classifier: Intended Audience :: Developers
Classifier: Topic :: Software Development
Classifier: License :: OSI Approved :: MIT License
Classifier: Programming Language :: Python :: 2
Classifier: Programming Language :: Python :: 2.7
Classifier: Programming Language :: Python :: 3
Classifier: Programming Language :: Python :: 3.3
Classifier: Programming Language :: Python :: 3.4
Classifier: Programming Language :: Python :: 3.5
